uP/PasoPaso/uP.v
module ROM(
	input wire [11:0] DIR,
	output wire [7:0] Y
	);
	
	
	reg [7:0] memoria [0:4095];
	
	initial begin
		$readmemh("memory.list", memoria);
	end
	assign Y = memoria[DIR];
endmodule 


module Contador (
	input wire clk,    // Clock
	input wire clk_en, // Clock Enable
	input wire rst,
	input wire load_en,
	input wire  [11:0] L,
	output reg	[11:0] Q
	);
	always @ (posedge clk or posedge rst) begin
		if (rst) begin
		Q <= 12'b0;
		end
		else if(load_en) begin
		Q <= L;
		end
		else if(clk_en) begin
		Q <= Q + 1;
		end
	end

endmodule

module microCode(
	input wire [6:0]S, 
	output reg [12:0]Q
	);
	always @ (S)
	begin
		casex (S)
			7'bxxxxxx0:	Q = 13'b1000000001000;
			7'b00001x1: Q = 13'b0100000001000;
			7'b00000x1: Q = 13'b1000000001000;
			7'b00011x1: Q = 13'b1000000001000;
			7'b00010x1: Q = 13'b0100000001000;
			7'b0010xx1: Q = 13'b0001001000010;
			7'b0011xx1: Q = 13'b1001001100000;
			7'b0100xx1: Q = 13'b0011010000010;
			7'b0101xx1: Q = 13'b0011010000100;
			7'b0110xx1: Q = 13'b1011010100000;
			7'b0111xx1: Q = 13'b1000000111000;
			7'b1000x11: Q = 13'b0100000001000;
			7'b1000x01: Q = 13'b1000000001000;
			7'b1001x11: Q = 13'b1000000001000;
			7'b1001x01: Q = 13'b0100000001000;
			7'b1010xx1: Q = 13'b0011011000010;
			7'b1011xx1: Q = 13'b1011011100000;
			7'b1100xx1: Q = 13'b0100000001000;
			7'b1101xx1: Q = 13'b0000000001001;
			7'b1110xx1: Q = 13'b0011100000010;
			7'b1111xx1: Q = 13'b1011100100000;
			default : Q = 13'b1000000001000;
		endcase
	end
endmodule

//Puede ser varias cosas
module bufftri(
	input wire en,
	input wire [3:0]S,
	output wire [3:0]Q
	);

	assign Q = en ? S:4'bz;

endmodule

module FFD1B (input wire clk, rst, en,
            input wire D, 
            output reg Q);
            always @ (posedge clk or posedge rst) begin
            if (rst) begin
            Q <= 1'b0;
            end
            else if(en) begin
            Q <= D;
            end
            end
endmodule

module FFT(input wire clk, rst,
             output wire K);
	wire T; 
	not (T, K);
    FFD1B r(clk, rst, 1'b1, T, K);

endmodule

module FFD2B(
      input wire clk, rst, en,
      input wire [1:0]D, 
      output wire [1:0]Q
      );

      FFD1B r0(clk, rst, en, D[0], Q[0]);
      FFD1B r1(clk, rst, en, D[1], Q[1]);

endmodule

//Puede ser varias cosas
module FFD4B(
      input wire clk, rst, en,
      input wire [3:0]D, 
      output wire [3:0]Q
      );

      FFD2B r2(clk, rst, en, D[1:0], Q[1:0]);
      FFD2B r3(clk, rst, en, D[3:2], Q[3:2]);

endmodule

module fetch(
      input wire clk, rst, en,
      input wire [7:0]D, 
      output wire [3:0]Q1,
      output wire [3:0]Q2
      );
      FFD4B r4(clk, rst, en, D[7:4], Q1[3:0]);
      FFD4B r5(clk, rst, en, D [3:0], Q2[3:0]);

endmodule

module Acumulador(
      input wire clk, rst, en,
      input wire [3:0]D, 
      output wire [3:0]Q
      );

      FFD2B r2(clk, rst, en, D[1:0], Q[1:0]);
      FFD2B r3(clk, rst, en, D[3:2], Q[3:2]);
endmodule

module Alu(input wire [3:0] W, 
            input wire [3:0]B, 
            input wire [2:0] Sel, 
            output wire carry, zero, 
            output reg [3:0] O
      );
			wire z;
			reg  c;

      		always @ (*) begin
      		case(Sel)
      		0:
      		{c, O} <= W;
      		1:
      		{c, O} <= W-B;
      		2:
      		{c, O} <= B; 
      		3:
      		{c, O} <= W+B;
      		4:
      		{c, O} <= {1'b0, ~(W & B)};
      		default
      		{c, O} <= 5'b0;
      	endcase
      end
      assign z = (O == 4'b0) ? 1'b1:1'b0;
      assign carry = c;
      assign zero = z;

endmodule

module RAM(
	input wire cs, we, //chipselect y write enable
	input wire [11:0] dir, //dirección de la memoria
	inout [3:0] data
	);
	reg [3:0] dataO; 
	reg [3:0] mem [0:4095]; //arreglo de la memoria

	assign data = (cs & !we)? dataO: 4'bz; //Buffer tri-estado 

	always @ (dir or data or cs or we)
	begin 
		if ( cs && we) begin
			mem[dir] = data;
		end
	end

	always @ (dir or cs or we)
	begin
		if (cs && !we) begin
			dataO = mem[dir];
		end
	end 

endmodule 


module uP(
	input wire clock, reset,
	input wire [3:0] pushbuttons,
	output wire phase, c_flag, z_flag,
	output wire [3:0] instr,
	output wire [3:0] oprnd,
	output wire [3:0] data_bus,
	output wire [3:0] FF_out,
	output wire [3:0] accu,
	output wire [7:0] program_byte,
	output wire [11:0] PC,
	output wire [11:0] address_RAM	
	);
	wire [12:0] microCode_O;
	wire [3:0]  ALU_O;
	wire Zero;
	wire Carry;
	wire [6:0] microCode_I;
	assign address_RAM = {oprnd, program_byte};
	assign microCode_I = {instr, c_flag, z_flag, phase}; //instr carry zero phase **CAMBIAR DEPSUES
	Contador pcmod(clock, microCode_O[12], reset, microCode_O[11], address_RAM, PC);
	ROM 	 romterm(PC, program_byte);
	fetch    fetchmod(clock, reset, ~phase, program_byte, instr, oprnd);
	FFT		 phasemod(clock, reset, phase);
	FFD2B    flags(clock, reset, microCode_O[9], {Zero, Carry}, {z_flag, c_flag});	
	microCode decodemod(microCode_I, microCode_O);
	bufftri  bfetch(microCode_O[1], oprnd, data_bus);
	RAM      rammod(microCode_O[5], microCode_O[4],address_RAM, data_bus);
	Acumulador     acumod(clock, reset, microCode_O[10], ALU_O, accu);
	Alu      alumod(accu, data_bus, microCode_O[8:6], Carry, Zero, ALU_O);
	bufftri bALU(microCode_O[3], ALU_O, data_bus);
	bufftri bIn(microCode_O[2], pushbuttons, data_bus);
	FFD4B   outmod(clock, reset, microCode_O[0], data_bus, FF_out);

endmodule

//Fetch 8 accu 4 output 4

uP/PasoPaso/uP_tb.v
module testbench();

    reg clock, reset;
    reg [3:0] pushbuttons;
    wire phase, c_flag, z_flag;
    wire [3:0] instr, oprnd, accu, data_bus, FF_out;
    wire [7:0] program_byte;
    wire [11:0] PC, address_RAM;

    integer nota = 0;
    integer immediateDelay = 16;
    integer jumpDelay = 656;
    integer memoryDelay = 276;

    uP uPmodule(.clock(clock),
                .reset(reset),
                .pushbuttons(pushbuttons),
                .phase(phase),
                .c_flag(c_flag),
                .z_flag(z_flag),
                .instr(instr),
                .oprnd(oprnd),
                .accu(accu),
                .data_bus(data_bus),
                .FF_out(FF_out),
                .program_byte(program_byte),
                .PC(PC),
                .address_RAM(address_RAM));
    always 
        #5  clock = ~clock;
    initial begin
        #1
        $display("Proyecto uP");
        $display("|clk| |rst|  |PB    |    |PC  |   |prog_byte |  || accu   d_bus  FF_out  C Z");
        $display("-----------------------------------------------------------------------------");
        $monitor("|%b  | |%b  |  |%b  |    |%d|   |%h        |  || %b   %b   %b    %b %b", clock, reset, pushbuttons, PC, program_byte, accu, data_bus, FF_out, c_flag, z_flag);
        clock = 0; reset = 0; pushbuttons = 1;
        #2 reset = 1;
        #1 reset = 0;
    end
    
          
    initial
    #325$finish;
    initial begin
      $dumpfile("uP_tb.vcd");
      $dumpvars(0, testbench);
    end
  endmodule

uP/uP_tb.vcd
$date
	Sun Nov 22 13:55:43 2020
$end
$version
	Icarus Verilog
$end
$timescale
	1ps
$end
$scope module testbench $end
$var wire 4 ! data_bus [3:0] $end
$var wire 1 " z_flag $end
$var wire 8 # program_byte [7:0] $end
$var wire 1 $ phase $end
$var wire 4 % oprnd [3:0] $end
$var wire 4 & instr [3:0] $end
$var wire 1 ' c_flag $end
$var wire 12 ( address_RAM [11:0] $end
$var wire 4 ) accu [3:0] $end
$var wire 12 * PC [11:0] $end
$var wire 4 + FF_out [3:0] $end
$var reg 1 , clock $end
$var reg 4 - pushbuttons [3:0] $end
$var reg 1 . reset $end
$var integer 32 / immediateDelay [31:0] $end
$var integer 32 0 jumpDelay [31:0] $end
$var integer 32 1 memoryDelay [31:0] $end
$var integer 32 2 nota [31:0] $end
$scope module uPmodule $end
$var wire 1 , clock $end
$var wire 4 3 data_bus [3:0] $end
$var wire 4 4 pushbuttons [3:0] $end
$var wire 1 . reset $end
$var wire 1 " z_flag $end
$var wire 8 5 program_byte [7:0] $end
$var wire 1 $ phase $end
$var wire 4 6 oprnd [3:0] $end
$var wire 13 7 microCode_O [12:0] $end
$var wire 7 8 microCode_I [6:0] $end
$var wire 4 9 instr [3:0] $end
$var wire 1 ' c_flag $end
$var wire 12 : address_RAM [11:0] $end
$var wire 4 ; accu [3:0] $end
$var wire 1 < Zero $end
$var wire 12 = PC [11:0] $end
$var wire 4 > FF_out [3:0] $end
$var wire 1 ? Carry $end
$var wire 4 @ ALU_O [3:0] $end
$scope module acumod $end
$var wire 1 , clk $end
$var wire 1 A en $end
$var wire 1 . rst $end
$var wire 4 B Q [3:0] $end
$var wire 4 C D [3:0] $end
$scope module r2 $end
$var wire 2 D D [1:0] $end
$var wire 1 , clk $end
$var wire 1 A en $end
$var wire 1 . rst $end
$var wire 2 E Q [1:0] $end
$scope module r0 $end
$var wire 1 F D $end
$var wire 1 , clk $end
$var wire 1 A en $end
$var wire 1 . rst $end
$var reg 1 G Q $end
$upscope $end
$scope module r1 $end
$var wire 1 H D $end
$var wire 1 , clk $end
$var wire 1 A en $end
$var wire 1 . rst $end
$var reg 1 I Q $end
$upscope $end
$upscope $end
$scope module r3 $end
$var wire 2 J D [1:0] $end
$var wire 1 , clk $end
$var wire 1 A en $end
$var wire 1 . rst $end
$var wire 2 K Q [1:0] $end
$scope module r0 $end
$var wire 1 L D $end
$var wire 1 , clk $end
$var wire 1 A en $end
$var wire 1 . rst $end
$var reg 1 M Q $end
$upscope $end
$scope module r1 $end
$var wire 1 N D $end
$var wire 1 , clk $end
$var wire 1 A en $end
$var wire 1 . rst $end
$var reg 1 O Q $end
$upscope $end
$upscope $end
$upscope $end
$scope module alumod $end
$var wire 4 P B [3:0] $end
$var wire 3 Q Sel [2:0] $end
$var wire 4 R W [3:0] $end
$var wire 1 ? carry $end
$var wire 1 < zero $end
$var wire 1 S z $end
$var reg 4 T O [3:0] $end
$var reg 1 ? c $end
$upscope $end
$scope module bALU $end
$var wire 4 U Q [3:0] $end
$var wire 4 V S [3:0] $end
$var wire 1 W en $end
$upscope $end
$scope module bIn $end
$var wire 4 X Q [3:0] $end
$var wire 4 Y S [3:0] $end
$var wire 1 Z en $end
$upscope $end
$scope module bfetch $end
$var wire 4 [ Q [3:0] $end
$var wire 1 \ en $end
$var wire 4 ] S [3:0] $end
$upscope $end
$scope module decodemod $end
$var wire 7 ^ S [6:0] $end
$var reg 13 _ Q [12:0] $end
$upscope $end
$scope module fetchmod $end
$var wire 1 , clk $end
$var wire 1 ` en $end
$var wire 1 . rst $end
$var wire 4 a Q2 [3:0] $end
$var wire 4 b Q1 [3:0] $end
$var wire 8 c D [7:0] $end
$scope module r4 $end
$var wire 4 d D [3:0] $end
$var wire 1 , clk $end
$var wire 1 ` en $end
$var wire 1 . rst $end
$var wire 4 e Q [3:0] $end
$scope module r2 $end
$var wire 2 f D [1:0] $end
$var wire 1 , clk $end
$var wire 1 ` en $end
$var wire 1 . rst $end
$var wire 2 g Q [1:0] $end
$scope module r0 $end
$var wire 1 h D $end
$var wire 1 , clk $end
$var wire 1 ` en $end
$var wire 1 . rst $end
$var reg 1 i Q $end
$upscope $end
$scope module r1 $end
$var wire 1 j D $end
$var wire 1 , clk $end
$var wire 1 ` en $end
$var wire 1 . rst $end
$var reg 1 k Q $end
$upscope $end
$upscope $end
$scope module r3 $end
$var wire 2 l D [1:0] $end
$var wire 1 , clk $end
$var wire 1 ` en $end
$var wire 1 . rst $end
$var wire 2 m Q [1:0] $end
$scope module r0 $end
$var wire 1 n D $end
$var wire 1 , clk $end
$var wire 1 ` en $end
$var wire 1 . rst $end
$var reg 1 o Q $end
$upscope $end
$scope module r1 $end
$var wire 1 p D $end
$var wire 1 , clk $end
$var wire 1 ` en $end
$var wire 1 . rst $end
$var reg 1 q Q $end
$upscope $end
$upscope $end
$upscope $end
$scope module r5 $end
$var wire 4 r D [3:0] $end
$var wire 1 , clk $end
$var wire 1 ` en $end
$var wire 1 . rst $end
$var wire 4 s Q [3:0] $end
$scope module r2 $end
$var wire 2 t D [1:0] $end
$var wire 1 , clk $end
$var wire 1 ` en $end
$var wire 1 . rst $end
$var wire 2 u Q [1:0] $end
$scope module r0 $end
$var wire 1 v D $end
$var wire 1 , clk $end
$var wire 1 ` en $end
$var wire 1 . rst $end
$var reg 1 w Q $end
$upscope $end
$scope module r1 $end
$var wire 1 x D $end
$var wire 1 , clk $end
$var wire 1 ` en $end
$var wire 1 . rst $end
$var reg 1 y Q $end
$upscope $end
$upscope $end
$scope module r3 $end
$var wire 2 z D [1:0] $end
$var wire 1 , clk $end
$var wire 1 ` en $end
$var wire 1 . rst $end
$var wire 2 { Q [1:0] $end
$scope module r0 $end
$var wire 1 | D $end
$var wire 1 , clk $end
$var wire 1 ` en $end
$var wire 1 . rst $end
$var reg 1 } Q $end
$upscope $end
$scope module r1 $end
$var wire 1 ~ D $end
$var wire 1 , clk $end
$var wire 1 ` en $end
$var wire 1 . rst $end
$var reg 1 !" Q $end
$upscope $end
$upscope $end
$upscope $end
$upscope $end
$scope module flags $end
$var wire 2 "" D [1:0] $end
$var wire 1 , clk $end
$var wire 1 #" en $end
$var wire 1 . rst $end
$var wire 2 $" Q [1:0] $end
$scope module r0 $end
$var wire 1 %" D $end
$var wire 1 , clk $end
$var wire 1 #" en $end
$var wire 1 . rst $end
$var reg 1 &" Q $end
$upscope $end
$scope module r1 $end
$var wire 1 '" D $end
$var wire 1 , clk $end
$var wire 1 #" en $end
$var wire 1 . rst $end
$var reg 1 (" Q $end
$upscope $end
$upscope $end
$scope module outmod $end
$var wire 4 )" D [3:0] $end
$var wire 1 , clk $end
$var wire 1 *" en $end
$var wire 1 . rst $end
$var wire 4 +" Q [3:0] $end
$scope module r2 $end
$var wire 2 ," D [1:0] $end
$var wire 1 , clk $end
$var wire 1 *" en $end
$var wire 1 . rst $end
$var wire 2 -" Q [1:0] $end
$scope module r0 $end
$var wire 1 ." D $end
$var wire 1 , clk $end
$var wire 1 *" en $end
$var wire 1 . rst $end
$var reg 1 /" Q $end
$upscope $end
$scope module r1 $end
$var wire 1 0" D $end
$var wire 1 , clk $end
$var wire 1 *" en $end
$var wire 1 . rst $end
$var reg 1 1" Q $end
$upscope $end
$upscope $end
$scope module r3 $end
$var wire 2 2" D [1:0] $end
$var wire 1 , clk $end
$var wire 1 *" en $end
$var wire 1 . rst $end
$var wire 2 3" Q [1:0] $end
$scope module r0 $end
$var wire 1 4" D $end
$var wire 1 , clk $end
$var wire 1 *" en $end
$var wire 1 . rst $end
$var reg 1 5" Q $end
$upscope $end
$scope module r1 $end
$var wire 1 6" D $end
$var wire 1 , clk $end
$var wire 1 *" en $end
$var wire 1 . rst $end
$var reg 1 7" Q $end
$upscope $end
$upscope $end
$upscope $end
$scope module pcmod $end
$var wire 12 8" L [11:0] $end
$var wire 1 , clk $end
$var wire 1 9" clk_en $end
$var wire 1 :" load_en $end
$var wire 1 . rst $end
$var reg 12 ;" Q [11:0] $end
$upscope $end
$scope module phasemod $end
$var wire 1 <" T $end
$var wire 1 , clk $end
$var wire 1 . rst $end
$var wire 1 $ K $end
$scope module r $end
$var wire 1 <" D $end
$var wire 1 , clk $end
$var wire 1 =" en $end
$var wire 1 . rst $end
$var reg 1 $ Q $end
$upscope $end
$upscope $end
$scope module rammod $end
$var wire 1 >" cs $end
$var wire 4 ?" data [3:0] $end
$var wire 12 @" dir [11:0] $end
$var wire 1 A" we $end
$var reg 4 B" dataO [3:0] $end
$upscope $end
$scope module romterm $end
$var wire 12 C" DIR [11:0] $end
$var wire 8 D" Y [7:0] $end
$upscope $end
$upscope $end
$upscope $end
$enddefinitions $end
#0
$dumpvars
bx D"
bx C"
bx B"
xA"
bx @"
bx ?"
x>"
1="
x<"
bx ;"
x:"
x9"
bx 8"
x7"
x6"
x5"
x4"
bx 3"
bx 2"
x1"
x0"
x/"
x."
bx -"
bx ,"
bx +"
x*"
bx )"
x("
x'"
x&"
x%"
bx $"
x#"
bx ""
x!"
x~
x}
x|
bx {
bx z
xy
xx
xw
xv
bx u
bx t
bx s
bx r
xq
xp
xo
xn
bx m
bx l
xk
xj
xi
xh
bx g
bx f
bx e
bx d
bx c
bx b
bx a
x`
bx _
bx ^
bx ]
x\
bx [
xZ
b110 Y
bx X
xW
bx V
bx U
bx T
xS
bx R
bx Q
bx P
xO
xN
xM
xL
bx K
bx J
xI
xH
xG
xF
bx E
bx D
bx C
bx B
xA
bx @
x?
bx >
bx =
x<
bx ;
bx :
bx 9
bx 8
bx 7
bx 6
bx 5
b110 4
bx 3
b0 2
b100010100 1
b1010010000 0
b10000 /
0.
b110 -
0,
bx +
bx *
bx )
bx (
x'
bx &
bx %
x$
bx #
x"
bx !
$end
#2
0."
00"
04"
06"
1'"
b0 ,"
b0 2"
0L
0N
0F
0H
0%"
1<
1S
b0 !
b0 3
b0 P
b0 U
b0 X
b0 [
b0 )"
b0 ?"
b0 J
b0 D
b10 ""
0?
b0 @
b0 C
b0 T
b0 V
1v
1x
1|
1~
0h
0j
1n
0p
b11 t
b11 z
b0 f
b1 l
0*"
0Z
1W
b0 Q
0A
0A"
0>"
0\
0#"
0:"
19"
b1111 r
b100 d
1<"
b1000000001000 7
b1000000001000 _
1`
0'
0"
b1001111 #
b1001111 5
b1001111 c
b1001111 D"
b0 *
b0 =
b0 ;"
b0 C"
0i
b0 g
0k
0o
b0 &
b0 9
b0 b
b0 e
b0 m
0q
0w
b0 u
0y
0}
b1001111 (
b1001111 :
b1001111 8"
b1001111 @"
b0 %
b0 6
b0 ]
b0 a
b0 s
b0 {
0!"
b0 8
b0 ^
0$
0&"
b0 $"
0("
0G
b0 E
0I
0M
b0 )
b0 ;
b0 B
b0 R
b0 K
0O
0/"
b0 -"
01"
05"
b0 +
b0 >
b0 +"
b0 3"
07"
1.
#3
0.
#5
0'"
1L
1N
1F
1H
b0 ""
0<
0S
b11 J
b11 D
b1111 @
b1111 C
b1111 T
b1111 V
1."
10"
14"
16"
b11 ,"
b11 2"
b1111 !
b1111 3
b1111 P
b1111 U
b1111 X
b1111 [
b1111 )"
b1111 ?"
1h
1p
0W
b10 Q
1A
1\
1#"
09"
b1 f
b11 l
0<"
0`
b11010000010 7
b11010000010 _
b1101 d
1$
1!"
b11 {
1}
1y
b1111 %
b1111 6
b1111 ]
b1111 a
b1111 s
b11 u
1w
b100001 8
b100001 ^
b100 &
b100 9
b100 b
b100 e
b1 m
1o
b111111011111 (
b111111011111 :
b111111011111 8"
b111111011111 @"
b11011111 #
b11011111 5
b11011111 c
b11011111 D"
b1 *
b1 =
b1 ;"
b1 C"
1,
#10
0,
#15
b1111 !
b1111 3
b1111 P
b1111 U
b1111 X
b1111 [
b1111 )"
b1111 ?"
1W
b0 Q
0A
0\
0#"
19"
1<"
b1000000001000 7
b1000000001000 _
1`
b100000 8
b100000 ^
0$
1G
b11 E
1I
1M
b1111 )
b1111 ;
b1111 B
b1111 R
b11 K
1O
1,
#16
b1000110 2
#20
0,
#25
0x
0|
0~
0p
1*"
09"
b1 t
b0 z
b1 l
0<"
0`
b1001 7
b1001 _
b1 r
b101 d
1$
b11 m
1q
b1101001 8
b1101001 ^
b1101 &
b1101 9
b1101 b
b1101 e
b1 g
1i
b111101010001 (
b111101010001 :
b111101010001 8"
b111101010001 @"
b1010001 #
b1010001 5
b1010001 c
b1010001 D"
b10 *
b10 =
b10 ;"
b10 C"
1,
#30
0,
#35
0*"
19"
1<"
b1000000001000 7
b1000000001000 _
1`
b1101000 8
b1101000 ^
0$
1/"
b11 -"
11"
15"
b1111 +
b1111 >
b1111 +"
b11 3"
17"
1,
#36
b1100111 2
#40
0,
#45
0N
0F
b1 J
b10 D
b110 @
b110 C
b110 T
b110 V
0."
06"
b10 ,"
b1 2"
b110 !
b110 3
b110 P
b110 U
b110 X
b110 [
b110 )"
b110 ?"
0v
0h
1Z
0W
b10 Q
1A
1#"
09"
b0 t
b0 f
0<"
0`
b11010000100 7
b11010000100 _
b0 r
b100 d
1$
0!"
b0 {
0}
b1 %
b1 6
b1 ]
b1 a
b1 s
b1 u
0y
b101001 8
b101001 ^
b101 &
b101 9
b101 b
b101 e
b1 m
0q
b101000000 (
b101000000 :
b101000000 8"
b101000000 @"
b1000000 #
b1000000 5
b1000000 c
b1000000 D"
b11 *
b11 =
b11 ;"
b11 C"
1,
#50
0,
#55
0Z
1W
b0 Q
0A
0#"
19"
1<"
b1000000001000 7
b1000000001000 _
1`
b101000 8
b101000 ^
0$
b10 E
0G
b110 )
b110 ;
b110 B
b110 R
b1 K
0O
1,
#56
b10001000 2
#60
0,
#65
1'"
0L
0H
b10 ""
1<
1S
b0 J
b0 D
b0 @
b0 C
b0 T
b0 V
00"
04"
b0 ,"
b0 2"
b0 !
b0 3
b0 P
b0 U
b0 X
b0 [
b0 )"
b0 ?"
1v
1x
1|
1~
0W
b10 Q
1A
1\
1#"
09"
b11 t
b11 z
0<"
0`
b11010000010 7
b11010000010 _
b1111 r
1$
b0 %
b0 6
b0 ]
b0 a
b0 s
b0 u
0w
b100001 8
b100001 ^
b100 &
b100 9
b100 b
b100 e
b0 g
0i
b1001111 (
b1001111 :
b1001111 8"
b1001111 @"
b1001111 #
b1001111 5
b1001111 c
b1001111 D"
b100 *
b100 =
b100 ;"
b100 C"
1,
#70
0,
#75
b0 !
b0 3
b0 P
b0 U
b0 X
b0 [
b0 )"
b0 ?"
1W
b0 Q
0A
0\
0#"
19"
1<"
b1000000001000 7
b1000000001000 _
1`
1"
b100010 8
b100010 ^
0$
b10 $"
1("
b0 E
0I
b0 )
b0 ;
b0 B
b0 R
b0 K
0M
1,
#80
0,
#85
0'"
1L
1N
1F
1H
b0 ""
0<
0S
b11 J
b11 D
b1111 @
b1111 C
b1111 T
b1111 V
1."
10"
14"
16"
b11 ,"
b11 2"
b1111 !
b1111 3
b1111 P
b1111 U
b1111 X
b1111 [
b1111 )"
b1111 ?"
0v
0|
1j
0n
1p
0W
b10 Q
1A
1\
1#"
09"
b10 t
b10 z
b10 f
b10 l
0<"
b11010000010 7
b11010000010 _
0`
b1010 r
b1010 d
b100011 8
b100011 ^
1$
1!"
b11 {
1}
1y
b1111 %
b1111 6
b1111 ]
b1111 a
b1111 s
b11 u
1w
b111110101010 (
b111110101010 :
b111110101010 8"
b111110101010 @"
b10101010 #
b10101010 5
b10101010 c
b10101010 D"
b101 *
b101 =
b101 ;"
b101 C"
1,
#90
0,
#95
b1111 !
b1111 3
b1111 P
b1111 U
b1111 X
b1111 [
b1111 )"
b1111 ?"
1W
b0 Q
0A
0\
0#"
19"
1<"
b1000000001000 7
b1000000001000 _
1`
0"
b100000 8
b100000 ^
0$
b0 $"
0("
1G
b11 E
1I
1M
b1111 )
b1111 ;
b1111 B
b1111 R
b11 K
1O
1,
#100
0,
#105
0L
0H
1%"
b10 J
b1 D
b1 ""
1?
b1001 @
b1001 C
b1001 T
b1001 V
0."
04"
b10 ,"
b10 2"
b1010 !
b1010 3
b1010 P
b1010 U
b1010 X
b1010 [
b1010 )"
b1010 ?"
0x
0p
0W
b11 Q
1A
1\
1#"
09"
b0 t
b0 l
0<"
0`
b11011000010 7
b11011000010 _
b1000 r
b10 d
1$
b10 {
0}
b1010 %
b1010 6
b1010 ]
b1010 a
b1010 s
b10 u
0w
1q
b10 m
0o
b1010001 8
b1010001 ^
b1010 &
b1010 9
b1010 b
b1010 e
b10 g
1k
b101000101000 (
b101000101000 :
b101000101000 8"
b101000101000 @"
b101000 #
b101000 5
b101000 c
b101000 D"
b110 *
b110 =
b110 ;"
b110 C"
1,
#110
0,
#115
0%"
b0 ""
0?
b1001 @
b1001 C
b1001 T
b1001 V
1."
00"
b1 ,"
b1001 !
b1001 3
b1001 P
b1001 U
b1001 X
b1001 [
b1001 )"
b1001 ?"
1W
b0 Q
0A
0\
0#"
19"
1<"
b1000000001000 7
b1000000001000 _
1`
1'
b1010100 8
b1010100 ^
0$
b1 $"
1&"
b1 E
0I
b1001 )
b1001 ;
b1001 B
b1001 R
b10 K
0M
1,
#116
b10101001 2
#120
0,
#125
0N
b0 J
b0 ""
0?
b1 @
b1 C
b1 T
b1 V
0."
b0 ,"
b1000 !
b1000 3
b1000 P
b1000 U
b1000 X
b1000 [
b1000 )"
b1000 ?"
1x
0j
1n
0W
b1 Q
1\
1#"
09"
b10 t
b0 f
b1 l
0<"
0`
b1001000010 7
b1001000010 _
b1010 r
b100 d
1$
b1000 %
b1000 6
b1000 ]
b1000 a
b1000 s
b0 u
0y
b10101 8
b10101 ^
b10 &
b10 9
b10 b
b10 e
b0 m
0q
b100001001010 (
b100001001010 :
b100001001010 8"
b100001001010 @"
b1001010 #
b1001010 5
b1001010 c
b1001010 D"
b111 *
b111 =
b111 ;"
b111 C"
1,
#130
0,
#135
1N
b10 J
b1001 @
b1001 C
b1001 T
b1001 V
1."
16"
b1 ,"
b10 2"
b1001 !
b1001 3
b1001 P
b1001 U
b1001 X
b1001 [
b1001 )"
b1001 ?"
1W
b0 Q
0\
0#"
19"
1<"
b1000000001000 7
b1000000001000 _
1`
0'
b10000 8
b10000 ^
0$
b0 $"
0&"
1,
#136
b11001010 2
#140
0,
#145
0F
1H
b10 D
b1010 @
b1010 C
b1010 T
b1010 V
0."
10"
b10 ,"
b1010 !
b1010 3
b1010 P
b1010 U
b1010 X
b1010 [
b1010 )"
b1010 ?"
0x
1|
1j
0n
0W
b10 Q
1A
1\
1#"
09"
b0 t
b11 z
b10 f
b0 l
0<"
0`
b11010000010 7
b11010000010 _
b1100 r
b10 d
1$
b1010 %
b1010 6
b1010 ]
b1010 a
b1010 s
b10 u
1y
b1 m
1o
b100001 8
b100001 ^
b100 &
b100 9
b100 b
b100 e
b0 g
0k
b101000101100 (
b101000101100 :
b101000101100 8"
b101000101100 @"
b101100 #
b101100 5
b101100 c
b101100 D"
b1000 *
b1000 =
b1000 ;"
b1000 C"
1,
#150
0,
#155
b1010 !
b1010 3
b1010 P
b1010 U
b1010 X
b1010 [
b1010 )"
b1010 ?"
1W
b0 Q
0A
0\
0#"
19"
1<"
b1000000001000 7
b1000000001000 _
1`
b100000 8
b100000 ^
0$
0G
b1010 )
b1010 ;
b1010 B
b1010 R
b10 E
1I
1,
#160
0,
#165
1L
1%"
b11 J
b1 ""
1?
b1110 @
b1110 C
b1110 T
b1110 V
00"
14"
b0 ,"
b11 2"
b1100 !
b1100 3
b1100 P
b1100 U
b1100 X
b1100 [
b1100 )"
b1100 ?"
1v
0|
0~
1p
0W
b1 Q
1\
1#"
09"
b1 t
b0 z
b10 l
0<"
0`
b1001000010 7
b1001000010 _
b1 r
b1010 d
1$
b11 {
1}
b1100 %
b1100 6
b1100 ]
b1100 a
b1100 s
b0 u
0y
b0 m
0o
b10001 8
b10001 ^
b10 &
b10 9
b10 b
b10 e
b10 g
1k
b110010100001 (
b110010100001 :
b110010100001 8"
b110010100001 @"
b10100001 #
b10100001 5
b10100001 c
b10100001 D"
b1001 *
b1001 =
b1001 ;"
b1001 C"
1,
#170
0,
#175
04"
b10 2"
0L
0%"
b10 J
b0 ""
0?
b1010 @
b1010 C
b1010 T
b1010 V
10"
b10 ,"
b1010 !
b1010 3
b1010 P
b1010 U
b1010 X
b1010 [
b1010 )"
b1010 ?"
1W
b0 Q
0\
0#"
19"
1<"
b1000000001000 7
b1000000001000 _
1`
1'
b10100 8
b10100 ^
0$
b1 $"
1&"
1,
#176
b11101011 2
#180
0,
#185
1F
b11 D
b0 ""
0?
b1011 @
b1011 C
b1011 T
b1011 V
1."
00"
06"
b1 ,"
b0 2"
b1 !
b1 3
b1 P
b1 U
b1 X
b1 [
b1 )"
b1 ?"
1x
1~
1n
0W
b11 Q
1A
1\
1#"
09"
b11 t
b10 z
b11 l
0<"
0`
b11011000010 7
b11011000010 _
b1011 r
b1110 d
1$
0!"
b0 {
0}
b1 %
b1 6
b1 ]
b1 a
b1 s
b1 u
1w
b1010101 8
b1010101 ^
b1010 &
b1010 9
b1010 b
b1010 e
b10 m
1q
b111101011 (
b111101011 :
b111101011 8"
b111101011 @"
b11101011 #
b11101011 5
b11101011 c
b11101011 D"
b1010 *
b1010 =
b1010 ;"
b1010 C"
1,
#190
0,
#195
b1011 @
b1011 C
b1011 T
b1011 V
10"
16"
b11 ,"
b10 2"
b1011 !
b1011 3
b1011 P
b1011 U
b1011 X
b1011 [
b1011 )"
b1011 ?"
1W
b0 Q
0A
0\
0#"
19"
1<"
b1000000001000 7
b1000000001000 _
1`
0'
b1010000 8
b1010000 ^
0$
b0 $"
0&"
b1011 )
b1011 ;
b1011 B
b1011 R
b11 E
1G
1,
#196
b100001100 2
#200
0,
#205
1L
0N
0F
0H
b1 J
b0 D
b100 @
b100 C
b100 T
b100 V
0v
0x
0~
1h
0j
0W
b100 Q
1A
1\
1#"
09"
b0 t
b0 z
b1 f
0<"
0`
b11100000010 7
b11100000010 _
b0 r
b1101 d
1$
b10 {
1!"
b1011 %
b1011 6
b1011 ]
b1011 a
b1011 s
b11 u
1y
b1110001 8
b1110001 ^
b1110 &
b1110 9
b1110 b
b1110 e
b11 m
1o
b101111010000 (
b101111010000 :
b101111010000 8"
b101111010000 @"
b11010000 #
b11010000 5
b11010000 c
b11010000 D"
b1011 *
b1011 =
b1011 ;"
b1011 C"
1,
#210
0,
