Lab9/EJ3/Ej3.v
//FlipFloptipoD 1bits
module FFD1B (input wire clk, rst, en,
            input wire D, 
            output reg Q);
            always @ (posedge clk or posedge rst) begin
            if (rst) begin
            Q <= 1'b0;
            end
            else if(en) begin
            Q <= D;
            end
            end
endmodule

module JKFF1B (
      input wire clk, rst, en,
      input wire J, K,
      output wire P
      );
      wire Q;

      assign Q = (J & ~P) | (~K & P);


      FFD1B t(clk, rst, en, Q, P);
endmodule

Lab9/EJ3/Ej3_tb.v
module testbench();
wire P;
reg clk, rst, en, J, K;

JKFF1B t(clk, rst, en, J, K, P);
always
  #2 clk <= ~clk;
  initial begin
    $display("Lab9_Ej2¿3");
    $display("clk rst en J K|P");
    $display("--------------|-");
    $monitor("%b  %b  %b  %b %b |%b", clk, rst, en, J, K, P);
    rst=0; clk=0; en= 1; J = 0; K = 0;
    #4 rst = 1;
    #4 rst = 0;
    #4 J = 1; K = 0;
    #4 J = 0; K = 1;
    #4 J = 1; K = 1;
    #4 J = 0; K = 0;
  end 
  initial
  #30 $finish;
  initial begin
    $dumpfile("EJ3_tb.vcd");
      $dumpvars(0, testbench);
    end

endmodule

Lab9/EJ3/EJ3_tb.vcd
$date
	Sat Oct 31 03:22:51 2020
$end
$version
	Icarus Verilog
$end
$timescale
	1ps
$end
$scope module testbench $end
$var wire 1 ! P $end
$var reg 1 " J $end
$var reg 1 # K $end
$var reg 1 $ clk $end
$var reg 1 % en $end
$var reg 1 & rst $end
$scope module t $end
$var wire 1 " J $end
$var wire 1 # K $end
$var wire 1 ' Q $end
$var wire 1 $ clk $end
$var wire 1 % en $end
$var wire 1 & rst $end
$var wire 1 ! P $end
$scope module t $end
$var wire 1 ' D $end
$var wire 1 $ clk $end
$var wire 1 % en $end
$var wire 1 & rst $end
$var reg 1 ! Q $end
$upscope $end
$upscope $end
$upscope $end
$enddefinitions $end
#0
$dumpvars
x'
0&
1%
0$
0#
0"
x!
$end
#2
1$
#4
0'
0!
0$
1&
#6
1$
#8
0$
0&
#10
1$
#12
0$
1'
1"
#14
1!
1$
#16
0$
0'
1#
0"
#18
0!
1$
#20
0$
1'
1"
#22
0'
1!
1$
#24
0$
1'
0#
0"
