LAB6/ej63/Lab6Ej5.v
//UVG Lab 6 
//Carlos Cuellar 19275

module FFDEj5(input wire clck, rset, set, 
			  input wire [3:0] D, 
			  output reg [3:0] Q);
always @ (posedge clck or posedge rset) begin
	if (rset)begin 
		Q <= 4'b0;
	end
	else if (set) begin
		Q <= 4'b1111;/* code */
	end
	else
		Q <= D;
	end

endmodule

module FFD (
	input wire D1,   
	input wire clk, 
	input wire reset,
	output reg  Q1  	
);

always @(posedge clk) 
begin
 if(reset==1'b1)
  Q1 <= 1'b0; 
 else 
  Q1 <= D1; 
end 

endmodule

module Ej61(input wire A, B, clck1, rset,
			output wire Y1);
wire S1F, S0F, S1, S0;

assign S1F = (S1 & A & B)|(S0 & B);
assign S0F = (~S1 & ~S0 & A);
assign Y1   = (S1 & A & B); 

FFD r0(S0F, clck1, rset, S0);
FFD r1(S1F, clck1, rset, S1);

endmodule

module Ej62 (
	input wire A, clck2, rset,
	output wire Y0, Y1, Y2
);

wire S2F, S1F, S0F, S2, S1, S0;

assign S2F = (~S2 & S1 & S0 & A) | (~S2 & ~S1 & ~S0 & ~A) | (S2 & ~S1 & S0) | (S2 & ~S0 & A) | (S2 & S1 & ~A); 
assign S1F = (~S1 & S0 & A) | (S1 & ~S0 & A) | (S1 & S0 & ~A) | (~S1 & ~S0 & ~A);
assign S0F = (~S0);

assign Y2 = (S2);
assign Y1 = (~S2 & S1) | (S2 & ~S1);
assign Y0 = (~S1 & S0) | (S1 & ~S0);

FFD k0(S0F, clck2, rset, S0);
FFD k1(S1F, clck2, rset, S1);
FFD k2(S2F, clck2, rset, S2);

endmodule

LAB6/ej63/Lab6Ej5_tb.v
module testbench();
wire Y0;
wire Y1;
wire Y2;
reg A;
reg clck, rst;

Ej62  r2(A, clck, rst, Y0, Y1, Y2);

always
  #1 clck <= ~clck;

//testbench flip flop d con reset asincrono
  initial begin
  $display(" Ejrecicio 6_2");
  $display("clck rst   A| Y2 Y1 Y0 ");
  $display("------------|-----");
  $monitor("%b     %b   %b | %b %b %b ", clck, rst, A, Y2, Y1, Y0);
     rst = 1; A = 1; clck = 1;
  #1 rst = 0; A = 1; 
  #1 rst = 0; A = 1; 
  #1 rst = 0; A = 1; 
  #1 rst = 0; A = 1; 
  #1 rst = 0; A = 1; 
  #1 rst = 0; A = 1; 
  #1 rst = 0; A = 1; 
  #1 rst = 0; A = 1;
  #1 rst = 0; A = 1;
  #1 rst = 0; A = 1; 
  #1 rst = 0; A = 1; 
  #1 rst = 0; A = 1; 
  #1 rst = 0; A = 1; 
  #1 rst = 0; A = 1;
  #1 rst = 0; A = 1;  
  #1 rst = 0; A = 0;
  #1 rst = 0; A = 0;
  #1 rst = 0; A = 0;
  #1 rst = 0; A = 0;
  #1 rst = 0; A = 0;
  #1 rst = 0; A = 0;
  #1 rst = 0; A = 0;
  #1 rst = 0; A = 0;  
  #1 rst = 0; A = 0;
  #1 rst = 0; A = 0;
  #1 rst = 0; A = 0;
  #1 rst = 0; A = 0;
 
  end

  
  
  initial
    #28 $finish;
  initial begin
      $dumpfile("Lab6Ej5_tb.vcd");
      $dumpvars(0, testbench);
    end
  endmodule

LAB6/ej63/Lab6Ej5_tb.vcd
$date
	Sun Sep 06 00:09:58 2020
$end
$version
	Icarus Verilog
$end
$timescale
	1ps
$end
$scope module testbench $end
$var wire 1 ! Y2 $end
$var wire 1 " Y1 $end
$var wire 1 # Y0 $end
$var reg 1 $ A $end
$var reg 1 % clck $end
$var reg 1 & rst $end
$scope module r2 $end
$var wire 1 $ A $end
$var wire 1 ' S0F $end
$var wire 1 ( S1F $end
$var wire 1 ) S2F $end
$var wire 1 # Y0 $end
$var wire 1 " Y1 $end
$var wire 1 ! Y2 $end
$var wire 1 % clck2 $end
$var wire 1 & rset $end
$var wire 1 * S2 $end
$var wire 1 + S1 $end
$var wire 1 , S0 $end
$scope module k0 $end
$var wire 1 ' D1 $end
$var wire 1 % clk $end
$var wire 1 & reset $end
$var reg 1 , Q1 $end
$upscope $end
$scope module k1 $end
$var wire 1 ( D1 $end
$var wire 1 % clk $end
$var wire 1 & reset $end
$var reg 1 + Q1 $end
$upscope $end
$scope module k2 $end
$var wire 1 ) D1 $end
$var wire 1 % clk $end
$var wire 1 & reset $end
$var reg 1 * Q1 $end
$upscope $end
$upscope $end
$upscope $end
$enddefinitions $end
#0
$dumpvars
0,
0+
0*
0)
0(
1'
1&
1%
1$
0#
0"
0!
$end
#1
0%
0&
#2
1(
1#
0'
1,
1%
#3
0%
#4
1(
1#
1"
1'
0,
1+
1%
#5
0%
#6
0(
1)
0#
0'
1,
1%
#7
0%
#8
1"
1'
0,
0+
1!
1*
1%
#9
0%
#10
1(
1#
0'
1,
1%
#11
0%
#12
1(
1)
0"
1#
1'
0,
1+
1%
#13
0%
#14
0(
0)
0#
0'
1,
1%
#15
0%
#16
1#
1'
0,
1%
0(
1)
0$
#17
0%
#18
1"
1)
0'
0+
1,
1%
#19
0%
#20
1(
0)
0#
1'
0,
1%
#21
0%
#22
0)
0#
0'
0!
0*
1+
1,
1%
#23
0%
#24
0(
1#
1'
0,
1%
#25
0%
#26
0"
0'
0+
1,
1%
#27
0%
#28
1)
1(
0#
1'
0,
1%
