Proyecto1/Proyecto1Penales.v
//Carlos Cuellar 19275
//UVG Proyecteo1

//FlipFloptipoD 3bits
module FFD3B (input wire clk, rst, en,
			input wire [2:0] D, 
			output reg [2:0] Q);
  always @ (posedge clk or posedge rst) begin
    if (rst) begin
      Q <= 3'b0;
      end
    else if(en) begin
      Q <= D;
      end
  end
endmodule

//FlipFloptipoD 2bits
module FFD2B (input wire clk, rst, en,
			input wire [1:0] D, 
			output reg [1:0] Q);
  always @ (posedge clk or posedge rst) begin
    if (rst) begin
      Q <= 2'b0;
      end
    else if(en) begin
      Q <= D;
      end
  end
endmodule

//FlipFloptipoD 1bits
module FFD1B (input wire clk, rst, en,
			input wire D, 
			output reg Q);
  always @ (posedge clk or posedge rst) begin
    if (rst) begin
      Q <= 1'b0;
      end
    else if(en) begin
      Q <= D;
      end
  end
endmodule

//FlipFloptipoD 5bits
module FFD5B (input wire clk, rst, en,
			input wire [4:0] D, 
			output reg [4:0] Q);
  always @ (posedge clk or posedge rst) begin
    if (rst) begin
      Q <= 5'b0;
      end 

    else if (en) begin
      Q <= D;
      end
  end
endmodule

//Mux2:1 para debug
module mux2_1(
	input wire s1, A0, B0, output wire Y0
);

	assign Y0 = s1? B0:A0;
endmodule

//Modulo de antirebote de un pushb
module antirebote (
	input wire bo, clk, rst, en,
	output wire bar
);
wire A, B;
	 
FFD1B r0(clk, rst, en, bo, A);
assign B = ~A;
assign bar	 = (B & bo);

endmodule

//Modulo de la primera FSM la cual habilita el modo 3 penales o 5 penales
module enable_conts(
	input wire M2, M1, clk, rst,
	output wire E3P, E5P
	);
wire [1:0]FS;
wire [1:0]S;
	assign  FS[1] = (S[1] & ~S[0])|(~S[0] & M2 & ~M1);
	assign  FS[0] =(~S[1] & S[0])| (~S[1] & ~M2 & M1) ;
FFD2B r1(clk, rst, 1'b1, FS, S);
	assign E5P = (S[1] & ~S[0])|(~S[0] & M2 & ~M1);
	assign E3P = (~S[1] & S[0])|(~S[1] & ~M2 & M1);

endmodule

//Modulo de la segunda FSM la cual es un contador de 0 a 3 penales (Modo 1 de juego)
module pen3(
	input wire K, noT, clk, rst, en,
	output wire [2:0] Cont3p,
	output wire FIN, ENJ3
);

wire [1:0]FS;
wire [1:0]S;
	assign FS[1] = (~S[1] & S[0] & K & ~noT)|(S[1]);
	assign FS[0] = (~S[1] & ~S[0] & K & ~noT)|(S[1] & K & ~noT)|(~S[1] & S[0] & noT)|(~S[1] & S[0] & ~K)|(S[1] & S[0]);
FFD2B r2(clk, rst, en, FS, S);
	assign Cont3p[2] = 1'b0;
	assign Cont3p[1] = (~S[1] & S[0] & K & ~noT)|(S[1]);
	assign Cont3p[0] = (~S[1] & ~S[0] & K & ~noT)|(S[1] & K & ~noT)|(~S[1] & S[0] & noT)|(~S[1] & S[0] & ~K)|(S[1] & S[0]);
	assign FIN = (S[1] & K & ~noT)|(S[1]&S[0]);
	assign ENJ3 = (~S[1] & S[0] & K & ~noT)|(~S[0] & noT)|(~S[0] & ~K)|(~S[1] & ~S[0] & K & ~noT)|(~S[1] & S[0] & noT)|(~S[1] & S[0] & ~K);

endmodule

//Modulo de la tercera FSM la cual es un contador de 0 a 5 penales (Modo 2 de juego)
module pen5(
	input wire K, noT, clk, rst, en,
	output wire [2:0] Cont5p,
	output wire FIN, ENJ5
	);
wire [2:0]FS;
wire [2:0]S;
	assign FS[2] = (S[2] & ~S[1])|(~S[2] & S[1] & S[0] & K & ~noT);
	assign FS[1] = (~S[2] & S[1] & ~S[0])|(~S[2] & S[1] & ~K)|(~S[2] & S[1] & noT)|(~S[2] & ~S[1] & S[0] & K & ~noT);
	assign FS[0] = (~S[2] & S[0] & ~K)|(~S[2] & S[0] & noT)|(~S[2] & ~S[0] & K & ~noT)|(S[2] & ~S[1] & S[0])|(S[2] & ~S[1] & K & ~noT);
FFD3B r3(clk, rst, en, FS, S);
	assign Cont5p[2] = (S[2] & ~S[1])|(~S[2] & S[1] & S[0] & K & ~noT);
	assign Cont5p[1] = (~S[2] & S[1] & ~S[0])|(~S[2] & S[1] & ~K)|(~S[2] & S[1] & noT)|(~S[2] & ~S[1] & S[0] & K & ~noT);
	assign Cont5p[0] = (~S[2] & S[0] & ~K)|(~S[2] & S[0] & noT)|(~S[2] & ~S[0] & K & ~noT)|(S[2] & ~S[1] & S[0])|(S[2] & ~S[1] & K & ~noT);
	assign FIN = (S[2] & ~S[1] & S[0])|(S[2] & ~S[1] & K & ~noT);
	assign ENJ5 = (~S[2])|(~S[1] & ~S[0] & ~K)|(~S[1] & ~S[0] & noT);

endmodule

module emp_contpen(
	input wire BM1, BM2, K, noT, clk, rst, en,
	output wire [2:0] Cont5p,
	output wire FIN5P, ENJ5,
	output wire [2:0] Cont3p,
	output wire FIN3P, ENJ3 
	);
wire UM1;
wire UM2;
wire UE3P;
wire UE5P;

antirebote r4(BM1, clk, rst, en, UM1);
antirebote r5(BM2, clk, rst, en, UM2);
enable_conts r6(UM1, UM2, clk, rst, UE3P, UE5P);
pen3 r7(K, noT, clk, rst, UE3P, Cont3p, FIN3P, ENJ3);
pen5 r8(K, noT, clk, rst, UE5P, Cont5p, FIN5P, ENJ5);
endmodule

Proyecto1/Proyecto1Penales_tb.v
module testbench();
//wire [2:0] Cont5p;
//wire FIN5P, ENJ5;
//wire [2:0] Cont3p;
//wire FIN3P, ENJ3;
//reg M1, M2, K, noT, clk, rst;

wire Y;
reg  bot, clk, rst, en;

//emp_contpen r1(M2, M1, K, noT, clk, rst, Cont5p, FIN5P, ENJ5, Cont3p, FIN3P, ENJ3);
antirebote  d9(bot, clk, rst, en, Y);
always 
	#1 clk <= ~clk;
	initial begin
  $display("Proyecto Penales");
  $display("clk   rst   bot|Y");
  $display("---------------|-----");
  $monitor("%b     %b       %b| %b", clk, rst, bot, Y);
     rst = 1; clk = 1; en= 1;
     #1 rst = 0; bot = 0;
     #3  bot =1; 
     #3  bot =0; 
     #3  bot =1;
     #3  bot =0;
     #3  bot =1;
     #3  bot =0;
     #3  bot =1;
     #3  bot =0;
     #3  bot =1;
     #3  bot =0;
     #3  bot =1;
     #3  bot =0;

end

  initial
    #50 $finish;
  initial begin
      $dumpfile("Proyecto1Penales_tb.vcd");
      $dumpvars(0, testbench);
    end
  endmodule

Proyecto1/Proyecto1Penales_tb.vcd
$date
	Sun Oct 11 06:10:42 2020
$end
$version
	Icarus Verilog
$end
$timescale
	1ps
$end
$scope module testbench $end
$var wire 1 ! Y $end
$var reg 1 " bot $end
$var reg 1 # clk $end
$var reg 1 $ en $end
$var reg 1 % rst $end
$scope module d9 $end
$var wire 1 & B $end
$var wire 1 ! bar $end
$var wire 1 " bo $end
$var wire 1 # clk $end
$var wire 1 $ en $end
$var wire 1 % rst $end
$var wire 1 ' A $end
$scope module r0 $end
$var wire 1 " D $end
$var wire 1 # clk $end
$var wire 1 $ en $end
$var wire 1 % rst $end
$var reg 1 ' Q $end
$upscope $end
$upscope $end
$upscope $end
$enddefinitions $end
#0
$dumpvars
0'
1&
1%
1$
1#
x"
x!
$end
#1
0#
0!
0"
0%
#2
1#
#3
0#
#4
0&
1'
1#
0!
1"
#5
0#
#6
1#
#7
0#
0"
#8
1&
0'
1#
#9
0#
#10
0&
1'
1#
0!
1"
#11
0#
#12
1#
#13
0#
0"
#14
1&
0'
1#
#15
0#
#16
0&
1'
1#
0!
1"
#17
0#
#18
1#
#19
0#
0"
#20
1&
0'
1#
#21
0#
#22
0&
1'
1#
0!
1"
#23
0#
#24
1#
#25
0#
0"
#26
1&
0'
1#
#27
0#
#28
0&
1'
1#
0!
1"
#29
0#
#30
1#
#31
0#
0"
#32
1&
0'
1#
#33
0#
#34
0&
1'
1#
0!
1"
#35
0#
#36
1#
#37
0#
0"
#38
1&
0'
1#
