Lab10/Ej2/Lab10Ej2.v
module FFD1B (input wire clk, rst, en,
            input wire D, 
            output reg Q);
            always @ (posedge clk or posedge rst) begin
            if (rst) begin
            Q <= 1'b0;
            end
            else if(en) begin
            Q <= D;
            end
            end
endmodule

module FFD2B(
      input wire clk, rst, en,
      input wire [1:0]D, 
      output wire [1:0]Q
      );

      FFD1B r0(clk, rst, en, D[0], Q[0]);
      FFD1B r1(clk, rst, en, D[1], Q[1]);

endmodule

module Acumulador(
      input wire clk, rst, en,
      input wire [3:0]D, 
      output wire [3:0]Q
      );

      FFD2B r2(clk, rst, en, D[1:0], Q[1:0]);
      FFD2B r3(clk, rst, en, D[3:2], Q[3:2]);
endmodule

module Alu(input wire [3:0] W, 
            input wire [3:0]B, 
            input wire [2:0] Sel, 
            output reg C, Z, 
            output reg [3:0] O
      );
      reg [4:0] AI;

      always @ (W, B, Sel)
      begin
      case (Sel)
            3'b000:
            begin 
            AI = 5'b00000;
            AI = W;
            C = 0;
            Z = 0;
            O = AI[3:0];
      end
      3'b010:
            begin 
            AI = 5'b00000;
            AI = B;
            C = 0;
            Z = 0;
            O = AI[3:0];
      end
      3'b100:
            begin 
            AI = 5'b00000;
            AI = ~(W&B);
            C = 0;
            Z = 0;
            O = AI[3:0];
      end
      3'b001:
            begin 
            AI = 5'b00000;
            AI = W-B;
            C = AI[4];
            Z = (AI==5'b00000);
            O = AI[3:0];
      end
      3'b011:
            begin 
            AI = 5'b00000;
            AI = W+B;
            C = AI[4];
            Z = (AI==5'b00000);
            O = AI[3:0];
      end
      endcase // Sel
end
endmodule

module bufftri4b(
      input wire en,
      input wire [3:0]S,
      output wire [3:0]Q
      );

      assign Q = en ? S:4'bz;

endmodule

module unionalu (
      input wire clk, rst, en, enb1, enb2,  
      input wire [3:0] in,
      input wire [2:0] Sel, 
      output wire C, Z, 
      output wire [3:0] O
      );
      wire [3:0] BB; 
      wire [3:0]ALUB; 
      wire [3:0]ACB; 
      wire [3:0]OALU;
     bufftri4b p0(enb1, in, BB);
     Acumulador P1(clk, rst, en, OALU, ACB);
     Alu          p2(ACB, BB, Sel, C, Z, OALU);
     bufftri4b    p3(enb2, OALU, O);

endmodule

Lab10/Ej2/Lab10Ej2_tb.v
module testbench();
 reg clk, rst, en, enb1, enb2;  
reg [3:0] in;
reg [2:0] Sel; 
wire C, Z; 
wire [3:0] O;

unionalu rt(clk, rst, en, enb1, enb2, in, Sel, C, Z, O);


  always
  #2 clk <= ~clk;
  initial begin
    $display("Lab10_Ej2");
    $display("clk rst en enb1 enb2 in   Sel    |C Z O");
    $display("---------------------------------|----------------");
    $monitor("%b   %b   %b   %b    %b   %b   %b  |%b %b %b", clk, rst, en, enb1, enb2, in, Sel, C, Z, O);
    rst=0; clk=0; en = 0; enb1 = 0; enb2 = 0; in = 3; Sel= 3'b010;
    #4 rst = 1;
    #4 rst = 0;
    #4 enb2 = 1; enb1 = 1; en = 1;
    #4 Sel = 3'b000; in = 2;  //Se debe de seguir mostrando el 3 en la tabla
    #4 in =2; en = 0;
    #4 Sel = 3'b001; 
    #4 Sel = 3'b011;
    #4 Sel = 3'b100;

    
  end 
  initial
  #36 $finish;
  initial begin
    $dumpfile("Lab10Ej2_tb.vcd");
      $dumpvars(0, testbench);
    end

endmodule

Lab10/Ej2/Lab10Ej2_tb.vcd
$date
	Sat Nov 07 23:17:01 2020
$end
$version
	Icarus Verilog
$end
$timescale
	1ps
$end
$scope module testbench $end
$var wire 1 ! Z $end
$var wire 4 " O [3:0] $end
$var wire 1 # C $end
$var reg 3 $ Sel [2:0] $end
$var reg 1 % clk $end
$var reg 1 & en $end
$var reg 1 ' enb1 $end
$var reg 1 ( enb2 $end
$var reg 4 ) in [3:0] $end
$var reg 1 * rst $end
$scope module rt $end
$var wire 3 + Sel [2:0] $end
$var wire 1 % clk $end
$var wire 1 & en $end
$var wire 1 ' enb1 $end
$var wire 1 ( enb2 $end
$var wire 4 , in [3:0] $end
$var wire 1 * rst $end
$var wire 1 ! Z $end
$var wire 4 - OALU [3:0] $end
$var wire 4 . O [3:0] $end
$var wire 1 # C $end
$var wire 4 / BB [3:0] $end
$var wire 4 0 ACB [3:0] $end
$scope module P1 $end
$var wire 1 % clk $end
$var wire 1 & en $end
$var wire 1 * rst $end
$var wire 4 1 Q [3:0] $end
$var wire 4 2 D [3:0] $end
$scope module r2 $end
$var wire 2 3 D [1:0] $end
$var wire 1 % clk $end
$var wire 1 & en $end
$var wire 1 * rst $end
$var wire 2 4 Q [1:0] $end
$scope module r0 $end
$var wire 1 5 D $end
$var wire 1 % clk $end
$var wire 1 & en $end
$var wire 1 * rst $end
$var reg 1 6 Q $end
$upscope $end
$scope module r1 $end
$var wire 1 7 D $end
$var wire 1 % clk $end
$var wire 1 & en $end
$var wire 1 * rst $end
$var reg 1 8 Q $end
$upscope $end
$upscope $end
$scope module r3 $end
$var wire 2 9 D [1:0] $end
$var wire 1 % clk $end
$var wire 1 & en $end
$var wire 1 * rst $end
$var wire 2 : Q [1:0] $end
$scope module r0 $end
$var wire 1 ; D $end
$var wire 1 % clk $end
$var wire 1 & en $end
$var wire 1 * rst $end
$var reg 1 < Q $end
$upscope $end
$scope module r1 $end
$var wire 1 = D $end
$var wire 1 % clk $end
$var wire 1 & en $end
$var wire 1 * rst $end
$var reg 1 > Q $end
$upscope $end
$upscope $end
$upscope $end
$scope module p0 $end
$var wire 4 ? S [3:0] $end
$var wire 1 ' en $end
$var wire 4 @ Q [3:0] $end
$upscope $end
$scope module p2 $end
$var wire 4 A B [3:0] $end
$var wire 3 B Sel [2:0] $end
$var wire 4 C W [3:0] $end
$var reg 5 D AI [4:0] $end
$var reg 1 # C $end
$var reg 4 E O [3:0] $end
$var reg 1 ! Z $end
$upscope $end
$scope module p3 $end
$var wire 4 F S [3:0] $end
$var wire 1 ( en $end
$var wire 4 G Q [3:0] $end
$upscope $end
$upscope $end
$upscope $end
$enddefinitions $end
#0
$dumpvars
bz G
bz F
bz E
b0zzzz D
bx C
b10 B
bz A
bz @
b11 ?
x>
z=
x<
z;
bx :
bz 9
x8
z7
x6
z5
bx 4
bz 3
bz 2
bx 1
bx 0
bz /
bz .
bz -
b11 ,
b10 +
0*
b11 )
0(
0'
0&
0%
b10 $
0#
bz "
0!
$end
#2
1%
#4
b0zzzz D
0>
b0 :
0<
08
b0 0
b0 1
b0 C
b0 4
06
0%
1*
#6
1%
#8
0%
0*
#10
1%
#12
0%
0;
0=
15
17
b11 "
b11 .
b11 G
b0 9
b11 3
b11 -
b11 2
b11 E
b11 F
b11 D
b11 /
b11 @
b11 A
1&
1'
1(
#14
b11 D
16
b11 0
b11 1
b11 C
b11 4
18
1%
#16
0%
b10 /
b10 @
b10 A
b11 D
b10 )
b10 ,
b10 ?
b0 $
b0 +
b0 B
#18
1%
#20
0%
0&
#22
1%
#24
0%
07
b1 "
b1 .
b1 G
b1 3
b1 -
b1 2
b1 E
b1 F
b1 D
b1 $
b1 +
b1 B
#26
1%
#28
0%
1;
b101 "
b101 .
b101 G
b1 9
b101 -
b101 2
b101 E
b101 F
b101 D
b11 $
b11 +
b11 B
#30
1%
#32
0%
1=
b1101 "
b1101 .
b1101 G
b11 9
b1101 -
b1101 2
b1101 E
b1101 F
b11101 D
b100 $
b100 +
b100 B
