LAB6/ej5/Lab6Ej5.v
//UVG Lab 6 
//Carlos Cuellar 19275

module FFDEj5(input wire clck, rset, set, 
			  input wire [3:0] D, 
			  output reg [3:0] Q);
always @ (posedge clck or posedge rset) begin
	if (rset)begin 
		Q <= 4'b0;
	end
	else if (set) begin
		Q <= 4'b1111;/* code */
	end
	else
		Q <= D;
	end

endmodule

LAB6/ej5/Lab6Ej5_tb.v
//Testbench del ejercicio5
module testbench();
wire [3:0] Q1;
reg [3:0] D1;
reg clck, rst, set;

FFDEj5  r1(clck, rst, set, D1, Q1);

always
  #1 clck <= ~clck;

//testbench flip flop d con reset asincrono
  initial begin
  $display(" Ejrecicio 5");
  $display("St C R  D    |  Q ");
  $display("------------|-----");
  $monitor("%b %b %b %b  | %b  ", set, clck, rst, D1, Q1);
     rst = 1; set = 1; D1[3] = 1; D1[2] = 1; D1[1] = 0; D1[0] = 0;  clck = 0;
  #5 rst = 0; set = 0; D1[3] = 0; D1[2] = 1; D1[1] = 1; D1[0] = 0;
  #5 rst = 0; set = 1; D1[3] = 1; D1[2] = 1; D1[1] = 1; D1[0] = 1;
  #5 rst = 0; set = 0; D1[3] = 0; D1[2] = 0; D1[1] = 1; D1[0] = 1;
  #5 rst = 0; set = 0; D1[3] = 1; D1[2] = 1; D1[1] = 0; D1[0] = 1;
  end
  initial
    #21 $finish;
  initial begin
      $dumpfile("Lab6Ej5_tb.vcd");
      $dumpvars(0, testbench);
    end
  endmodule

LAB6/ej5/Lab6Ej5_tb.vcd
$date
	Sat Sep 05 22:58:35 2020
$end
$version
	Icarus Verilog
$end
$timescale
	1ps
$end
$scope module testbench $end
$var wire 4 ! Q1 [3:0] $end
$var reg 4 " D1 [3:0] $end
$var reg 1 # clck $end
$var reg 1 $ rst $end
$var reg 1 % set $end
$scope module r1 $end
$var wire 4 & D [3:0] $end
$var wire 1 # clck $end
$var wire 1 $ rset $end
$var wire 1 % set $end
$var reg 4 ' Q [3:0] $end
$upscope $end
$upscope $end
$enddefinitions $end
#0
$dumpvars
b0 '
b1100 &
1%
1$
0#
b1100 "
b0 !
$end
#1
1#
#2
0#
#3
1#
#4
0#
#5
b110 !
b110 '
1#
b110 "
b110 &
0%
0$
#6
0#
#7
1#
#8
0#
#9
1#
#10
0#
b1111 "
b1111 &
1%
#11
b1111 !
b1111 '
1#
#12
0#
#13
1#
#14
0#
#15
b11 !
b11 '
1#
b11 "
b11 &
0%
#16
0#
#17
1#
#18
0#
#19
1#
#20
0#
b1101 "
b1101 &
#21
b1101 !
b1101 '
1#
