Lab9/EJ4/Ej4.v
//Tristate buffer
module bufftri(
	input wire en,
	input wire [3:0]S,
	output wire [3:0]Q
	);

	assign Q = en ? S:4'bz;

endmodule

Lab9/EJ4/Ej4_tb.v
module testbench();

wire [3:0]Q;
reg [3:0]S;
reg en;

bufftri r(en, S, Q);

initial begin
    $display("Lab9_Ej1");
    $display("en S   | Q ");
    $display("-------|------");
    $monitor("%b %b | %b", en, S, Q);
    en = 0; S=4'b0000;
    #4 en = 1;
    #4 S = 4'b1111;
    #4 S = 4'b1110;
    #4 S = 4'b1100;
    #4 S = 4'b1000;
    #4 S = 4'b0000;
    #4 en = 0;
  end 
  initial
  #30 $finish;
  initial begin
    $dumpfile("Ej4_tb.vcd");
      $dumpvars(0, testbench);
    end

endmodule

Lab9/EJ4/Ej4_tb.vcd
$date
	Sat Oct 31 03:25:14 2020
$end
$version
	Icarus Verilog
$end
$timescale
	1ps
$end
$scope module testbench $end
$var wire 4 ! Q [3:0] $end
$var reg 4 " S [3:0] $end
$var reg 1 # en $end
$scope module r $end
$var wire 4 $ S [3:0] $end
$var wire 1 # en $end
$var wire 4 % Q [3:0] $end
$upscope $end
$upscope $end
$enddefinitions $end
#0
$dumpvars
bz %
b0 $
0#
b0 "
bz !
$end
#4
b0 !
b0 %
1#
#8
b1111 !
b1111 %
b1111 "
b1111 $
#12
b1110 !
b1110 %
b1110 "
b1110 $
#16
b1100 !
b1100 %
b1100 "
b1100 $
#20
b1000 !
b1000 %
b1000 "
b1000 $
#24
b0 !
b0 %
b0 "
b0 $
#28
bz !
bz %
0#
