Lab8/Contador.v
//Lab8_Ej1
module Contador (
	input wire clk,    // Clock
	input wire clk_en, // Clock Enable
	input wire rst,
	input wire load_en,
	input wire  [11:0] L,
	output reg	[11:0] Q
);
	always @ (posedge clk or posedge rst) begin
		if (rst) begin
		Q <= 12'b0;
		end
		else if(load_en) begin
		Q <= L;
		end
		else if(clk_en) begin
		Q <= Q + 1;
		end
	end

endmodule

Lab8/Contador_tb.v
//Testbench pc
module testbench();
reg 	clk;    // Clock
reg 	clk_en; // Clock Enable
reg 	rst;
reg		load_en;
reg  	[11:0] L;
wire 	[11:0] Q;

Contador r1(clk, clk_en, rst, load_en, L, Q);
always
	#2 clk <= ~clk;
initial begin
	$display("Contador_12B/PC");
	$display("clk rst clk_en  load_en     L      	        |Q");
	$monitor("%b   %b   %b        %b       %b         |%b", clk, rst, clk_en, load_en, L, Q);
	rst = 0; clk = 1; clk_en = ;0 load_en = 0; L = 12'b000000000000;
	#4 rst = 1;
	#4 rst = 0;
	#4 clk_en =1;
	#4 clk_en =1;
	#4 clk_en =1;
	#4 clk_en =1;
	#4 clk_en =1;
	#4 clk_en =1;
	#4 clk_en =1;
	#4 clk_en =1;
	#4 clk_en =1;
	#4 clk_en =1;
	#4 clk_en =1;
	#4 clk_en =1;
	#4 clk_en =1;
	#4 clk_en =1;
	#4 rst = 1;
	#4 rst = 0; clk_en = 0; load_en = 1;
	#4 L = 12'b000000011111;
	#20 clk_en = 1; load_en = 0;
	#10 load_en = 1;


end
initial
	#200 $finish;	
initial begin
      $dumpfile("Contador_tb.vcd");
      $dumpvars(0, testbench);
    end
  endmodule

Lab8/Contador_tb.vcd
$date
	Thu Oct 22 16:55:55 2020
$end
$version
	Icarus Verilog
$end
$timescale
	1ps
$end
$scope module testbench $end
$var wire 12 ! Q [11:0] $end
$var reg 12 " L [11:0] $end
$var reg 1 # clk $end
$var reg 1 $ clk_en $end
$var reg 1 % load_en $end
$var reg 1 & rst $end
$scope module r1 $end
$var wire 12 ' L [11:0] $end
$var wire 1 # clk $end
$var wire 1 $ clk_en $end
$var wire 1 % load_en $end
$var wire 1 & rst $end
$var reg 12 ( Q [11:0] $end
$upscope $end
$upscope $end
$enddefinitions $end
#0
$dumpvars
bx (
b0 '
0&
0%
0$
1#
b0 "
bx !
$end
#2
0#
#4
b0 !
b0 (
1#
1&
#6
0#
#8
1#
0&
#10
0#
#12
b1 !
b1 (
1#
1$
#14
0#
#16
b10 !
b10 (
1#
#18
0#
#20
b11 !
b11 (
1#
#22
0#
#24
b100 !
b100 (
1#
#26
0#
#28
b101 !
b101 (
1#
#30
0#
#32
b110 !
b110 (
1#
#34
0#
#36
b111 !
b111 (
1#
#38
0#
#40
b1000 !
b1000 (
1#
#42
0#
#44
b1001 !
b1001 (
1#
#46
0#
#48
b1010 !
b1010 (
1#
#50
0#
#52
b1011 !
b1011 (
1#
#54
0#
#56
b1100 !
b1100 (
1#
#58
0#
#60
b1101 !
b1101 (
1#
#62
0#
#64
b1110 !
b1110 (
1#
#66
0#
#68
b0 !
b0 (
1#
1&
#70
0#
#72
1#
1%
0$
0&
#74
0#
#76
b11111 !
b11111 (
1#
b11111 "
b11111 '
#78
0#
#80
1#
#82
0#
#84
1#
#86
0#
#88
1#
#90
0#
#92
1#
#94
0#
#96
b100000 !
b100000 (
1#
0%
1$
#98
0#
#100
b100001 !
b100001 (
1#
#102
0#
#104
b100010 !
b100010 (
1#
#106
0#
1%
#108
b11111 !
b11111 (
1#
