LAB4/EJ4.v
//Carlos Cuellar #19275 UVG
//Código de la práctica 4 de lab Digital 1

module Ecuacion1_1(input wire A, B, C, output wire Y);

wire out0;
wire out1;
wire out2;
wire out3;
wire out4;
wire out5;


not (out0, A);
not (out1, B);
not (out2, C);
and (out3, out0, out2);
and (out4, A, out1);
and (out5, A, C);
or (Y, out3, out4, out5);
endmodule

module Ecuacion1_2(input wire B, output wire Y);

not (Y, B);

endmodule

module Ecuacion1_3(input wire A, B, C, D, output wire Y);
wire o0, o1, o2, o3, o4, o5, o6, o7, o8, o9, o10, o11;

not (o0, A);
not (o1, B);
not (o2, C);
not (o3, D);
and (o4, o0, o1, o2, o3);
and (o5, o0, o1, C, D);
and (o6, o0, B, o2, D);
and (o7, o0, B, C, o3);
and (o8, A, B, o2, o3);
and (o9, A, B, C, D);
and (o10, A, o1, o2, D);
and (o11, A, o1, C, o3);
or (Y, o4, o5, o6, o7, o8, o9, o10, o11);

endmodule


module Ecuacion1_4(input wire A, B, C, D, output wire Y);
wire out0, out1, out2, out3;

not (out0, D);
and (out1, A, out0);
and (out2, B, D);
and (out3, A, C);
or (Y, out1, out2, out3);

endmodule

module Ecuacion2_1(input wire A, B, C, D, output wire Y);

assign Y = (~B & ~C & ~D) | (A & (~B | ~C | ~D));

endmodule

module Ecuacion2_3(input wire A, B, C, D, output wire Y);

assign Y = (B | (D & (A | ~C)));

endmodule

module Ecuacion2_2(input wire A, B, C, output wire Y);

assign Y = (C | ~B);

endmodule


module Ecuacion2_4(input wire A, B, C, output wire Y);

assign Y = ((~A & ~C) | B);

endmodule

module Ecuacion5_SOP(input wire A, B, C, output wire Y);

assign Y = ((A & ~B & ~C) | (A & ~B & C) | (A & B & C));

endmodule

module Ecuacion5_POS(input wire A, B, C, output wire Y);

assign Y = ((A | B | C) & (A | B | ~C) & (A |~B | C) & (A | ~B | ~C) & (~A| ~B | C));

endmodule

module Ecuacion5_OG(input wire A, B, C, output wire Y);

wire out0;
wire out1;
wire out2; 
not (out0, B);
and (out1, out0, A);
and (out2, A, C);
or (Y, out1, out2);

endmodule

LAB4/EJ4_tb.v
                  
module testbench();
	reg p1, p2, p3, p4, p5,p6, p7, p8, p9, p10, p11, p12, p13, p14, p15, p16, p17, p18;
	wire Y1, Y2, Y3, Y4, Y5, Y6, Y7, Y8,Y9, Y10, Y11;

	Ecuacion1_1 EQ1(p1, p2, p3, Y1);
	Ecuacion1_2 EQ2(p4, Y2);
	Ecuacion1_3 EQ3(p5, p6, p7, p8, Y3);
	Ecuacion1_4 EQ4(p5, p6, p7, p8, Y4);
	Ecuacion2_1 EQ5(p12, p11, p10, p9, Y5);
	Ecuacion2_3 EQ6(p12, p11, p10, p9, Y6);
	Ecuacion2_2 EQ7(p13, p14, p15, Y7);
	Ecuacion2_4 EQ8(p13, p14, p15, Y8);
	Ecuacion5_SOP EQ9(p16, p17, p18, Y9);
	Ecuacion5_POS EQ10(p16, p17, p18, Y10);
	Ecuacion5_OG EQ11(p16, p17, p18, Y11);



initial begin
	$display("EQ1_1");
	$display("A B C | Y1");
	$display("---------");

	$monitor("%b %b %b | %b", p1, p2, p3, Y1);
       p1 = 0; p2 = 0; p3 = 0;
    #1 p3 = 1;
    #1 p2 = 1; p3 = 0;
    #1 p3 = 1;
    #1 p1 = 1; p2 = 0; p3 = 0;
    #1 p3 = 1;
    #1 p2 = 1; p3 = 0;
    #1 p3 = 1;
  end

initial begin
#9
	$display("\n");
	$display("EQ1_2");
	$display("B | Y2");
	$display("------");
	$monitor("%b | %b", p4, Y2);
	p4=0;
	#1 p4 = 1;
  end

initial begin
#11
	$display("\n");
	$display("EQ1_3 y EQ1_4");
	$display("A B C D | Y3 Y4");
	$display("------------");
	$monitor("%b %b %b %b | %b  %b", p5, p6, p7, p8, Y3, Y4);
	   p5 = 0; p6 = 0; p7 = 0; p8 = 0;
	#1 p8 = 1;
	#1 p8 = 0; p7 = 1;
	#1 p8 = 1; 
	#1 p8 = 0; p7 = 0; p6 = 1;
	#1 p8 = 1;
	#1 p8 = 0; p7 = 1;
	#1 p8 = 1;
	#1 p8 = 0; p7 = 0; p6 = 0; p5 = 1;
	#1 p8 = 1;
	#1 p8 = 0; p7 = 1; 
	#1 p8 = 1; 
	#1 p8 = 0; p7 = 0; p6 = 1; 
	#1 p8 = 1;
	#1 p8 = 0; p7 = 1;
	#1 p8 = 1;
	end

initial begin
#27
	$display("\n");
	$display("EQ2_1 y EQ2_3");
	$display("A B C D | Y5 Y6");
	$display("------------");
	$monitor("%b %b %b %b | %b  %b", p12, p11, p10, p9, Y5, Y6);
	   p9 = 0; p10 = 0; p11 = 0; p12 = 0;
	#1 p9 = 1;
	#1 p9 = 0; p10 = 1;
	#1 p9 = 1; 
	#1 p9 = 0; p10 = 0; p11 = 1;
	#1 p9 = 1;
	#1 p9 = 0; p10 = 1;
	#1 p9 = 1;
	#1 p9 = 0; p10 = 0; p11 = 0; p12 = 1;
	#1 p9 = 1;
	#1 p9 = 0; p10 = 1; 
	#1 p9 = 1; 
	#1 p9 = 0; p10 = 0; p11 = 1; 
	#1 p9 = 1;
	#1 p9 = 0; p10 = 1;
	#1 p9 = 1;
	end

	initial begin
#43
	$display("\n");
	$display("EQ2_2 y EQ2_4");
	$display("A B C | Y7 Y8");
	$display("------------");
	$monitor("%b %b %b | %b  %b", p15, p14, p13, Y7, Y8);
	   p15 = 0; p14 = 0; p13 = 0;
    #1 p15 = 1;
    #1 p14 = 1; p15 = 0;
    #1 p15 = 1;
    #1 p13 = 1; p14 = 0; p15 = 0;
    #1 p15 = 1;
    #1 p14 = 1; p15 = 0;
    #1 p15 = 1;
	end

	initial begin
#51
	$display("\n");
	$display("Ejercicio 5");
	$display("A B C | Y9 Y10 Y11");
	$display("-----------------");
	$monitor("%b %b %b | %b  %b  %b", p16, p17, p18, Y9, Y10, Y11);
	   p16 = 0; p17 = 0; p18 = 0;
    #1 p18 = 1;
    #1 p17 = 1; p18 = 0;
    #1 p18 = 1;
    #1 p16 = 1; p17 = 0; p18 = 0;
    #1 p18 = 1;
    #1 p17 = 1; p18 = 0;
    #1 p18 = 1;
	end

initial 
	#59 $finish;


initial begin
    $dumpfile("EJ4_tb.vcd");
    $dumpvars(0, testbench);
  end
  
endmodule

LAB4/EJ4_tb.vcd
$date
	Tue Aug 11 00:58:13 2020
$end
$version
	Icarus Verilog
$end
$timescale
	1ps
$end
$scope module testbench $end
$var wire 1 ! Y9 $end
$var wire 1 " Y8 $end
$var wire 1 # Y7 $end
$var wire 1 $ Y6 $end
$var wire 1 % Y5 $end
$var wire 1 & Y4 $end
$var wire 1 ' Y3 $end
$var wire 1 ( Y2 $end
$var wire 1 ) Y11 $end
$var wire 1 * Y10 $end
$var wire 1 + Y1 $end
$var reg 1 , p1 $end
$var reg 1 - p10 $end
$var reg 1 . p11 $end
$var reg 1 / p12 $end
$var reg 1 0 p13 $end
$var reg 1 1 p14 $end
$var reg 1 2 p15 $end
$var reg 1 3 p16 $end
$var reg 1 4 p17 $end
$var reg 1 5 p18 $end
$var reg 1 6 p2 $end
$var reg 1 7 p3 $end
$var reg 1 8 p4 $end
$var reg 1 9 p5 $end
$var reg 1 : p6 $end
$var reg 1 ; p7 $end
$var reg 1 < p8 $end
$var reg 1 = p9 $end
$scope module EQ1 $end
$var wire 1 , A $end
$var wire 1 6 B $end
$var wire 1 7 C $end
$var wire 1 + Y $end
$var wire 1 > out0 $end
$var wire 1 ? out1 $end
$var wire 1 @ out2 $end
$var wire 1 A out3 $end
$var wire 1 B out4 $end
$var wire 1 C out5 $end
$upscope $end
$scope module EQ10 $end
$var wire 1 3 A $end
$var wire 1 4 B $end
$var wire 1 5 C $end
$var wire 1 * Y $end
$upscope $end
$scope module EQ11 $end
$var wire 1 3 A $end
$var wire 1 4 B $end
$var wire 1 5 C $end
$var wire 1 ) Y $end
$var wire 1 D out0 $end
$var wire 1 E out1 $end
$var wire 1 F out2 $end
$upscope $end
$scope module EQ2 $end
$var wire 1 8 B $end
$var wire 1 ( Y $end
$upscope $end
$scope module EQ3 $end
$var wire 1 9 A $end
$var wire 1 : B $end
$var wire 1 ; C $end
$var wire 1 < D $end
$var wire 1 ' Y $end
$var wire 1 G o0 $end
$var wire 1 H o1 $end
$var wire 1 I o10 $end
$var wire 1 J o11 $end
$var wire 1 K o2 $end
$var wire 1 L o3 $end
$var wire 1 M o4 $end
$var wire 1 N o5 $end
$var wire 1 O o6 $end
$var wire 1 P o7 $end
$var wire 1 Q o8 $end
$var wire 1 R o9 $end
$upscope $end
$scope module EQ4 $end
$var wire 1 9 A $end
$var wire 1 : B $end
$var wire 1 ; C $end
$var wire 1 < D $end
$var wire 1 & Y $end
$var wire 1 S out0 $end
$var wire 1 T out1 $end
$var wire 1 U out2 $end
$var wire 1 V out3 $end
$upscope $end
$scope module EQ5 $end
$var wire 1 / A $end
$var wire 1 . B $end
$var wire 1 - C $end
$var wire 1 = D $end
$var wire 1 % Y $end
$upscope $end
$scope module EQ6 $end
$var wire 1 / A $end
$var wire 1 . B $end
$var wire 1 - C $end
$var wire 1 = D $end
$var wire 1 $ Y $end
$upscope $end
$scope module EQ7 $end
$var wire 1 0 A $end
$var wire 1 1 B $end
$var wire 1 2 C $end
$var wire 1 # Y $end
$upscope $end
$scope module EQ8 $end
$var wire 1 0 A $end
$var wire 1 1 B $end
$var wire 1 2 C $end
$var wire 1 " Y $end
$upscope $end
$scope module EQ9 $end
$var wire 1 3 A $end
$var wire 1 4 B $end
$var wire 1 5 C $end
$var wire 1 ! Y $end
$upscope $end
$upscope $end
$enddefinitions $end
#0
$dumpvars
xV
xU
xT
xS
xR
xQ
xP
xO
xN
xM
xL
xK
xJ
xI
xH
xG
xF
xE
xD
0C
0B
1A
1@
1?
1>
x=
x<
x;
x:
x9
x8
07
06
x5
x4
x3
x2
x1
x0
x/
x.
x-
0,
1+
x*
x)
x(
x'
x&
x%
x$
x#
x"
x!
$end
#1
0+
0A
0@
17
#2
1+
1A
1@
0?
07
16
#3
0+
0A
0@
17
#4
1+
1B
1@
1?
0>
07
06
1,
#5
0@
1C
17
#6
0+
0B
1@
0C
0?
07
16
#7
1+
0@
1C
17
#9
1(
08
#10
0(
18
#11
1'
1M
0&
1L
1S
1K
0N
1H
0O
0P
0U
1G
0Q
0R
0I
0J
0T
0V
0<
0;
0:
09
#12
0'
0M
0L
0S
1<
#13
0K
1L
1S
1;
0<
#14
1'
0L
1N
0S
1<
#15
0'
0H
1K
1L
0N
1S
1:
0;
0<
#16
1'
1&
0L
1O
0S
1U
1<
#17
0&
0K
1P
1L
0O
1S
0U
1;
0<
#18
0'
0P
1&
0L
0S
1U
1<
#19
0G
1T
1H
1K
1L
1S
0U
19
0:
0;
0<
#20
1'
0&
0T
0L
1I
0S
1<
#21
1&
1T
0K
1J
1V
1L
0I
1S
1;
0<
#22
0'
0J
0T
0L
0S
1<
#23
1'
1T
0H
1Q
1K
0V
1L
1S
1:
0;
0<
#24
0'
0Q
0T
0L
0S
1U
1<
#25
1T
0K
1V
1L
1S
0U
1;
0<
#26
1'
0T
0L
1R
0S
1U
1<
#27
1%
0$
0/
0.
0-
0=
#28
0%
1$
1=
#29
0%
0$
1-
0=
#30
1=
#31
1$
1.
0-
0=
#32
1=
#33
1-
0=
#34
1=
#35
1%
0$
1/
0.
0-
0=
#36
1$
1=
#37
0$
1-
0=
#38
1$
1=
#39
1.
0-
0=
#40
1=
#41
1-
0=
#42
0%
1=
#43
1"
1#
00
01
02
#44
0"
12
#45
0#
1"
02
11
#46
1#
12
#47
0"
02
01
10
#48
12
#49
0#
1"
02
11
#50
1#
12
#51
0*
0!
0)
1D
0E
0F
05
04
03
#52
15
#53
0D
05
14
#54
15
#55
1!
1*
1)
1E
1D
05
04
13
#56
1F
15
#57
0*
0!
0)
0E
0F
0D
05
14
#58
1*
1)
1!
1F
15
