Lab8/ROM/ROM.v
//UVG DIGITAL 1 2020//UVG Digital 1 2020
//Carlos Cuellar 19275
//Lab8_Ej2

module ROM(
	input wire [11:0] DIR,
	output wire [7:0] Y
	);
	
	assign Y = memoria[DIR];
	reg [7:0] memoria [0:4095];
	
	initial begin
		$readmemh("datos.list", memoria);
	end

endmodule

Lab8/ROM/ROM_tb.v
//Testbench rom
module testbench();

reg [11:0]DIR;
wire [7:0] Y;

ROM r(DIR, Y);

initial begin

	$display("ROM_4Kx8");
	$display("DIR	        | Y");
	$monitor("%b	| %b", DIR, Y);
	DIR = 0;
	#1 DIR = 0;
	#1 DIR = 1;
	#1 DIR = 2;
	#1 DIR = 3;
	#1 DIR = 4;
	#1 DIR = 5;
	#1 DIR = 6;
	#1 DIR = 7;
	#1 DIR = 8;
	#1 DIR = 9;
	#1 DIR = 10;
	#1 DIR = 11;
	#1 DIR = 12;
	#1 DIR = 13;
	#1 DIR = 2000;
	#1 DIR = 1;
	#1 DIR = 4000;

end 
initial
	#20 $finish;	
initial begin
      $dumpfile("ROM_tb.vcd");
      $dumpvars(0, testbench);
    end
  endmodule

Lab8/ROM/ROM_tb.vcd
$date
	Fri Nov 20 09:27:45 2020
$end
$version
	Icarus Verilog
$end
$timescale
	1ps
$end
$scope module testbench $end
$var wire 8 ! Y [7:0] $end
$var reg 12 " DIR [11:0] $end
$scope module r $end
$var wire 12 # DIR [11:0] $end
$var wire 8 $ Y [7:0] $end
$upscope $end
$upscope $end
$enddefinitions $end
#0
$dumpvars
b10101010 $
b0 #
b0 "
b10101010 !
$end
#2
b10111011 !
b10111011 $
b1 "
b1 #
#3
b11001100 !
b11001100 $
b10 "
b10 #
#4
b11101111 !
b11101111 $
b11 "
b11 #
#5
b10100001 !
b10100001 $
b100 "
b100 #
#6
b11111111 !
b11111111 $
b101 "
b101 #
#7
b11010100 !
b11010100 $
b110 "
b110 #
#8
b110100 !
b110100 $
b111 "
b111 #
#9
b0 !
b0 $
b1000 "
b1000 #
#10
b1 !
b1 $
b1001 "
b1001 #
#11
b1100 !
b1100 $
b1010 "
b1010 #
#12
b11000000 !
b11000000 $
b1011 "
b1011 #
#13
b11101001 !
b11101001 $
b1100 "
b1100 #
#14
b10011110 !
b10011110 $
b1101 "
b1101 #
#15
bx !
bx $
b11111010000 "
b11111010000 #
#16
b10111011 !
b10111011 $
b1 "
b1 #
#17
bx !
bx $
b111110100000 "
b111110100000 #
