Lab9/EJ5/Ej5.v
module ROMCASE(
	input wire [6:0]S, 
	output reg [12:0]Q
	);
	always @ (*)
	begin
		casex (S)
			7'bxxxxxx0:	Q = 13'b1000000001000;
			7'b00001x1: Q = 13'b0100000001000;
			7'b00000x1: Q = 13'b1000000001000;
			7'b00011x1: Q = 13'b1000000001000;
			7'b00010x1: Q = 13'b0100000001000;
			7'b0010xx1: Q = 13'b0001001000010;
			7'b0011xx1: Q = 13'b1001001100000;
			7'b0100xx1: Q = 13'b0011010000010;
			7'b0101xx1: Q = 13'b0011010000100;
			7'b0110xx1: Q = 13'b1011010100000;
			7'b0111xx1: Q = 13'b1000000111000;
			7'b1000x11: Q = 13'b0100000001000;
			7'b1000x01: Q = 13'b1000000001000;
			7'b1001x11: Q = 13'b1000000001000;
			7'b1001x01: Q = 13'b0100000001000;
			7'b1010xx1: Q = 13'b0011011000010;
			7'b1011xx1: Q = 13'b1011011100000;
			7'b1100xx1: Q = 13'b0100000001000;
			7'b1101xx1: Q = 13'b0000000001001;
			7'b1110xx1: Q = 13'b0011100000010;
			7'b1111xx1: Q = 13'b1011100100000;
			//default : Q = 13'b1000000001000;
		endcase
	end
endmodule

Lab9/EJ5/Ej5_tb.v
module testbench();

wire [12:0]Q;
reg [6:0]S;

ROMCASE d(S, Q);
  initial begin
    $display("Lab9_Ej5");
    $display("S       | Q");
    $display("--------|--");
    $monitor("%b | %b", S, Q);
    S = 7'b0000000;
    #1 S = 7'bxxxxxx0;
    #1 S = 7'b00001x1;     
    #1 S = 7'b00000x1;       
    #1 S = 7'b00011x1;       
    #1 S = 7'b00010x1;       
    #1 S = 7'b0010xx1;       
    #1 S = 7'b0011xx1;       
    #1 S = 7'b0100xx1;       
    #1 S = 7'b0101xx1;       
    #1 S = 7'b0110xx1;       
    #1 S = 7'b0111xx1;       
    #1 S = 7'b1000x11;       
    #1 S = 7'b1000x01;       
    #1 S = 7'b1001x11;       
    #1 S = 7'b1001x01;       
    #1 S = 7'b1010xx1;       
    #1 S = 7'b1011xx1;       
    #1 S = 7'b1100xx1;       
    #1 S = 7'b1101xx1;     
    #1 S = 7'b1110xx1;     
    #1 S = 7'b1111xx1;  
    #1 S = 7'b0000111;
    #1 S = 7'b0000011;
    #1 S = 7'b0001111;
    #1 S = 7'b0001011;
    #1 S = 7'b0010111;
    #1 S = 7'b0011111;
    #1 S = 7'b0100111;
    #1 S = 7'b0101111;
    #1 S = 7'b0110111;
    #1 S = 7'b0111111;
    #1 S = 7'b1000111;
    #1 S = 7'b1000101;
    #1 S = 7'b1001111;
    #1 S = 7'b1001101;
    #1 S = 7'b1010111;
    #1 S = 7'b1011111;
    #1 S = 7'b1100111;
    #1 S = 7'b1101111;
    #1 S = 7'b1110111;
    #1 S = 7'b1111111;
  end 
  initial
  #100 $finish;
  initial begin
    $dumpfile("Ej5_tb.vcd");
      $dumpvars(0, testbench);
    end

endmodule

Lab9/EJ5/Ej5_tb.vcd
$date
	Sat Oct 31 03:30:59 2020
$end
$version
	Icarus Verilog
$end
$timescale
	1ps
$end
$scope module testbench $end
$var wire 13 ! Q [12:0] $end
$var reg 7 " S [6:0] $end
$scope module d $end
$var wire 7 # S [6:0] $end
$var reg 13 $ Q [12:0] $end
$upscope $end
$upscope $end
$enddefinitions $end
#0
$dumpvars
b1000000001000 $
b0 #
b0 "
b1000000001000 !
$end
#1
bx0 "
bx0 #
#2
b100000001000 !
b100000001000 $
b1x1 "
b1x1 #
#3
b1000000001000 !
b1000000001000 $
b0x1 "
b0x1 #
#4
b11x1 "
b11x1 #
#5
b100000001000 !
b100000001000 $
b10x1 "
b10x1 #
#6
b1001000010 !
b1001000010 $
b10xx1 "
b10xx1 #
#7
b1001001100000 !
b1001001100000 $
b11xx1 "
b11xx1 #
#8
b11010000010 !
b11010000010 $
b100xx1 "
b100xx1 #
#9
b11010000100 !
b11010000100 $
b101xx1 "
b101xx1 #
#10
b1011010100000 !
b1011010100000 $
b110xx1 "
b110xx1 #
#11
b1000000111000 !
b1000000111000 $
b111xx1 "
b111xx1 #
#12
b100000001000 !
b100000001000 $
b1000x11 "
b1000x11 #
#13
b1000000001000 !
b1000000001000 $
b1000x01 "
b1000x01 #
#14
b1001x11 "
b1001x11 #
#15
b100000001000 !
b100000001000 $
b1001x01 "
b1001x01 #
#16
b11011000010 !
b11011000010 $
b1010xx1 "
b1010xx1 #
#17
b1011011100000 !
b1011011100000 $
b1011xx1 "
b1011xx1 #
#18
b100000001000 !
b100000001000 $
b1100xx1 "
b1100xx1 #
#19
b1001 !
b1001 $
b1101xx1 "
b1101xx1 #
#20
b11100000010 !
b11100000010 $
b1110xx1 "
b1110xx1 #
#21
b1011100100000 !
b1011100100000 $
b1111xx1 "
b1111xx1 #
#22
b100000001000 !
b100000001000 $
b111 "
b111 #
#23
b1000000001000 !
b1000000001000 $
b11 "
b11 #
#24
b1111 "
b1111 #
#25
b100000001000 !
b100000001000 $
b1011 "
b1011 #
#26
b1001000010 !
b1001000010 $
b10111 "
b10111 #
#27
b1001001100000 !
b1001001100000 $
b11111 "
b11111 #
#28
b11010000010 !
b11010000010 $
b100111 "
b100111 #
#29
b11010000100 !
b11010000100 $
b101111 "
b101111 #
#30
b1011010100000 !
b1011010100000 $
b110111 "
b110111 #
#31
b1000000111000 !
b1000000111000 $
b111111 "
b111111 #
#32
b100000001000 !
b100000001000 $
b1000111 "
b1000111 #
#33
b1000000001000 !
b1000000001000 $
b1000101 "
b1000101 #
#34
b1001111 "
b1001111 #
#35
b100000001000 !
b100000001000 $
b1001101 "
b1001101 #
#36
b11011000010 !
b11011000010 $
b1010111 "
b1010111 #
#37
b1011011100000 !
b1011011100000 $
b1011111 "
b1011111 #
#38
b100000001000 !
b100000001000 $
b1100111 "
b1100111 #
#39
b1001 !
b1001 $
b1101111 "
b1101111 #
#40
b11100000010 !
b11100000010 $
b1110111 "
b1110111 #
#41
b1011100100000 !
b1011100100000 $
b1111111 "
b1111111 #
