Lab8/ALU/ALU.v
//UVG DIGITAL 1 2020//UVG Digital 1 2020
//Carlos Cuellar 19275
//Lab8_Ej3

module ALU_BB(
	input wire 	[3:0]A,
	input wire 	[3:0]B,
	input wire 	[2:0]SEL,
	output reg	[3:0]Y
	);
	always @ (*)
	begin
	case (SEL)
		3'b000:  Y = A & B ;
		3'b001:  Y = A | B;
		3'b010:  Y = A + B;

		3'b100:  Y = A & ~B;
		3'b101:  Y = A | ~B;
		3'b110:  Y = A - B;
		3'b111:  Y = (A > B)?3'b001 : 3'b000;
		default :  Y = A & B;
	endcase
	end
endmodule

Lab8/ALU/ALU_tb.v
//Testbench ALU
module testbench();

reg [3:0] A;
reg [3:0] B;
reg [2:0] SEL;
wire [3:0] Y;

ALU_BB r(A, B, SEL, Y);

initial begin

	$display("ALU 4 bits");
	$display("A   B   SEL  | Y");
	$monitor("%b  %b  %b   | %b", A, B, SEL, Y);
	A = 0; B= 0; SEL = 0;
	#1 A = 4'b1000; B = 4'b0111; SEL = 3'b000;
	#1 SEL = 3'b001;
	#1 SEL = 3'b010;
	#1 SEL = 3'b011;
	#1 SEL = 3'b100;
	#1 SEL = 3'b101;
	#1 SEL = 3'b110;
	#1 SEL = 3'b111;
end
initial
	#9 $finish;	
initial begin
      $dumpfile("ALU_tb.vcd");
      $dumpvars(0, testbench);
    end
  endmodule

Lab8/ALU/ALU_tb.vcd
$date
	Sat Oct 24 19:07:16 2020
$end
$version
	Icarus Verilog
$end
$timescale
	1ps
$end
$scope module testbench $end
$var wire 4 ! Y [3:0] $end
$var reg 4 " A [3:0] $end
$var reg 4 # B [3:0] $end
$var reg 3 $ SEL [2:0] $end
$scope module r $end
$var wire 4 % A [3:0] $end
$var wire 4 & B [3:0] $end
$var wire 3 ' SEL [2:0] $end
$var reg 4 ( Y [3:0] $end
$upscope $end
$upscope $end
$enddefinitions $end
#0
$dumpvars
b0 (
b0 '
b0 &
b0 %
b0 $
b0 #
b0 "
b0 !
$end
#1
b111 #
b111 &
b1000 "
b1000 %
#2
b1111 !
b1111 (
b1 $
b1 '
#3
b10 $
b10 '
#4
b0 !
b0 (
b11 $
b11 '
#5
b1000 !
b1000 (
b100 $
b100 '
#6
b101 $
b101 '
#7
b1 !
b1 (
b110 $
b110 '
#8
b111 $
b111 '
